{
  "main": {
    "id": "29283e19d750122e",
    "type": "split",
    "children": [
      {
        "id": "2296b7191ef34755",
        "type": "tabs",
        "children": [
          {
            "id": "a17daf9dce7d606b",
            "type": "leaf",
            "pinned": true,
            "state": {
              "type": "canvas",
              "state": {
                "file": "Programming/Web/Node/Roadmap.canvas",
                "viewState": {
                  "x": 877.4945660986286,
                  "y": -284.1810326047253,
                  "zoom": -0.7076816589742898
                }
              },
              "pinned": true
            }
          }
        ]
      }
    ],
    "direction": "vertical"
  },
  "left": {
    "id": "e623d5e06b76d396",
    "type": "split",
    "children": [
      {
        "id": "305b9510d8e4bc9c",
        "type": "tabs",
        "children": [
          {
            "id": "dad1860c6cdc5cf5",
            "type": "leaf",
            "state": {
              "type": "file-explorer",
              "state": {
                "sortOrder": "alphabetical"
              }
            }
          },
          {
            "id": "e1fce680541e9f2b",
            "type": "leaf",
            "state": {
              "type": "search",
              "state": {
                "query": "\\t",
                "matchingCase": false,
                "explainSearch": false,
                "collapseAll": false,
                "extraContext": false,
                "sortOrder": "alphabetical"
              }
            }
          },
          {
            "id": "cbc55adca057d8d8",
            "type": "leaf",
            "state": {
              "type": "bookmarks",
              "state": {}
            }
          }
        ]
      }
    ],
    "direction": "horizontal",
    "width": 317
  },
  "right": {
    "id": "3aa9242cac8da568",
    "type": "split",
    "children": [
      {
        "id": "23f6f0f49cfc758a",
        "type": "tabs",
        "dimension": 41.20505344995141,
        "children": [
          {
            "id": "6530cb1def2d8d8b",
            "type": "leaf",
            "pinned": true,
            "state": {
              "type": "graph",
              "state": {},
              "pinned": true
            }
          },
          {
            "id": "1acf5530efe24d7a",
            "type": "leaf",
            "state": {
              "type": "tag",
              "state": {
                "sortOrder": "frequency",
                "useHierarchy": false
              }
            }
          },
          {
            "id": "5298f4bda8f954d5",
            "type": "leaf",
            "state": {
              "type": "backlink",
              "state": {
                "file": "Programming/Web/Node/Roadmap.canvas",
                "collapseAll": false,
                "extraContext": false,
                "sortOrder": "alphabetical",
                "showSearch": false,
                "searchQuery": "",
                "backlinkCollapsed": false,
                "unlinkedCollapsed": true
              }
            }
          },
          {
            "id": "bf7bb2826de24780",
            "type": "leaf",
            "state": {
              "type": "outgoing-link",
              "state": {
                "file": "Programming/Web/Node/Roadmap.canvas",
                "linksCollapsed": false,
                "unlinkedCollapsed": true
              }
            }
          }
        ]
      },
      {
        "id": "192447c50af0b608",
        "type": "tabs",
        "dimension": 58.79494655004859,
        "children": [
          {
            "id": "576be28795952012",
            "type": "leaf",
            "state": {
              "type": "all-properties",
              "state": {
                "sortOrder": "frequency",
                "showSearch": false,
                "searchQuery": ""
              }
            }
          },
          {
            "id": "cf3e18f5b01fd71e",
            "type": "leaf",
            "state": {
              "type": "advanced-tables-toolbar",
              "state": {}
            }
          },
          {
            "id": "dc842caf5e993a4a",
            "type": "leaf",
            "state": {
              "type": "outline",
              "state": {
                "file": "Programming/Web/Node/Roadmap.canvas"
              }
            }
          }
        ],
        "currentTab": 2
      }
    ],
    "direction": "horizontal",
    "width": 360,
    "collapsed": true
  },
  "left-ribbon": {
    "hiddenItems": {
      "switcher:Open quick switcher": false,
      "graph:Open graph view": false,
      "canvas:Create new canvas": false,
      "daily-notes:Open today's daily note": false,
      "templates:Insert template": false,
      "command-palette:Open command palette": false,
      "table-editor-obsidian:Advanced Tables Toolbar": false
    }
  },
  "active": "a17daf9dce7d606b",
  "lastOpenFiles": [
    "Linux/ZSH.md",
    "Linux/Arch/Arch.md",
    "Linux/Linux.md",
    "Programming/Web/Node/Фреймворки/CSS/Tailwind/Пользовательские Стили.md",
    "Programming/Web/Node/Фреймворки/CSS/Tailwind/Адаптивный дизайн.md",
    "Cache/Pasted image 20240911161616.png",
    "Cache/Pasted image 20240911161156.png",
    "Programming/Web/Node/Фреймворки/CSS/Tailwind/Tailwind.md",
    "Programming/Web/Node/Фреймворки/CSS/Tailwind/Tailwind Основы.md",
    "Programming/Web/Node/Roadmap.canvas",
    "Programming/Web/Node/Фреймворки/CSS/Tailwind",
    "Programming/Web/Node/Фреймворки/Фуллстек/Next.js/Обработка ошибок.md",
    "Programming/Web/Node/Фиктивные объекты и данные, моки, стабы.md",
    "Programming/Web/Node/Пакетные менеджеры.md",
    "Programming/Web/Node/Libs.md",
    "Programming/Web/Node/Node.js.md",
    "Programming/C++/String.md",
    "Programming/C++/Variables.md",
    "Programming/C++/Functions.md",
    "Programming/C++/Loops.md",
    "Programming/C++/Constructions.md",
    "Programming/C++/Arrays.md",
    "Programming/C++/Types.md",
    "Programming/C++/С++.md",
    "Programming/Web/Node/Фреймворки/Фуллстек/Next.js/Next.js Project Structure.canvas",
    "Programming/Web/Node/Prisma/Client.md",
    "Programming/Web/Node/Prisma/Seed.md",
    "Programming/Web/Node/Prisma/Prisma.md",
    "Programming/Web/Web.md",
    "Programming/Web/SEO.md",
    "Programming/Web/Resources.md",
    "Programming/C++/Exercises",
    "Programming/C++",
    "Programming/Стили программирования",
    "Untitled",
    "Cache/Pasted image 20240822002237.png",
    "Cache/Pasted image 20240822000558.png",
    "Cache/Pasted image 20240822000547.png",
    "Cache/Pasted image 20240822000515.png",
    "Cache/Pasted image 20240821231447.png",
    "Cache/Pasted image 20240821231004.png",
    "Cache/Pasted image 20240820212656.png",
    "Cache/Pasted image 20240820212638.png",
    "Programming/Web/Node/Typescript/Структуры данных",
    "Programming/Web/Node/Typescript/Data types/Map obj",
    "Programming/Web/Библиотеки компонентов",
    "Templates",
    "Programming/Web/Node/Typescript/Data types/Strings",
    "main/Programming/Web/Фреймворки/Фуллстек/Next.js/Next.js Project Structure.canvas"
  ]
}